mona_sdk/__init__.py
mona_sdk/async_client.py
mona_sdk/client.py
mona_sdk/client_exceptions.py
mona_sdk/client_util.py
mona_sdk/logger.py
mona_sdk/messages.py
mona_sdk/mona_single_message.py
mona_sdk/validation.py
mona_sdk/auth/__init__.py
mona_sdk/auth/globals.py
mona_sdk/auth/utils.py
mona_sdk/auth/authenticators/__init__.py
mona_sdk/auth/authenticators/base_authenticator.py
mona_sdk/auth/authenticators/factory.py
mona_sdk/auth/authenticators/manual_token.py
mona_sdk/auth/authenticators/mona.py
mona_sdk/auth/authenticators/no_auth.py
mona_sdk/auth/authenticators/oidc.py
mona_sdk-0.0.58.dist-info/licenses/LICENSE
mona_sdk-0.0.58.dist-info/METADATA
mona_sdk-0.0.58.dist-info/WHEEL
mona_sdk-0.0.58.dist-info/top_level.txt
mona_sdk-0.0.58.dist-info/RECORD
