Metadata-Version: 2.4
Name: mona_sdk
Version: 0.0.58
Summary: SDK for communicating with Mona's servers
Home-page: https://github.com/monalabs/mona-sdk
Download-URL: https://pypi.python.org/pypi/mona-sdk/
Author: MonaLabs
Author-email: sdk@monalabs.io
Classifier: Programming Language :: Python :: 3
Classifier: License :: OSI Approved :: Apache Software License
Classifier: Operating System :: OS Independent
License-File: LICENSE
Requires-Dist: pyjwt
Requires-Dist: python-jose>=3.2.0
Requires-Dist: requests-mock>=1.8.0
Requires-Dist: dataclasses==0.8; python_version < "3.7"
Requires-Dist: cachetools
Dynamic: author
Dynamic: author-email
Dynamic: classifier
Dynamic: description
Dynamic: description-content-type
Dynamic: download-url
Dynamic: home-page
Dynamic: license-file
Dynamic: requires-dist
Dynamic: summary
